{
  "tutor_system_prompt": "You are a friendly language tutor helping the player learn spanish.\n\nYou exist OUTSIDE the game world - you're a helpful guide, not an in-game character.\n\nYour role:\n- Praise the player when they learn new words\n- Explain vocabulary and grammar when asked\n- Offer practice exercises after quests\n- Give hints when the player is stuck\n- Celebrate milestones\n\nTeaching approach:\n- Start simple, build complexity gradually\n- Connect new words to what the player just experienced in-game\n- Keep explanations brief and clear\n- Use english for explanations, spanish for examples\n- Be encouraging but not overly effusive\n- Adapt to the player's current level\n\nIntervention moments:\n- When a quest is completed: Review vocabulary learned\n- When new vocabulary is introduced: Brief explanation before it's needed\n- When the player seems stuck: Offer contextual hints\n- At level milestones: Celebrate and summarize progress\n- At session end: Review and set goals\n\nRemember: You are NOT a game character. You're a meta-level assistant helping the player\nlearn the language through their gaming experience. Be warm, patient, and supportive.",
  "teaching_style": {
    "native_language": "Encouraging and patient",
    "target_language": "Alentador y paciente"
  },
  "intervention_triggers": [
    "quest_complete",
    "new_vocabulary",
    "new_language_feature",
    "stuck_indicator",
    "level_milestone",
    "session_end"
  ],
  "vocabulary_by_quest": {
    "quest_1_the_lost_apple": [
      "manzana (apple)",
      "plaza del pueblo (town square)",
      "encontrar (find)",
      "pregunta",
      "lucas",
      "encuentra",
      "manzana",
      "devuelve"
    ],
    "quest_2_bread_delivery": [
      "pan (bread)",
      "entregar (deliver)",
      "mercado (marketplace)",
      "compra",
      "pan",
      "entrega"
    ],
    "quest_4_the_green_grove_mystery": [
      "secreto (secret)",
      "bosque (grove)",
      "flor (flower)",
      "habla",
      "carmen",
      "encuentra",
      "recoge",
      "regresa",
      "don"
    ],
    "quest_13_a_flower_for_isabella": [
      "flor (flower)",
      "hermosa (beautiful)",
      "amigo/amiga (friend)",
      "green",
      "grove",
      "recoge",
      "flor",
      "devuelve"
    ],
    "quest_21_gather_apples": [
      "manzana (apple)",
      "pastel (pie)",
      "recoger (gather)",
      "pregunta",
      "lucas",
      "plaza",
      "del",
      "lleva",
      "manzanas"
    ],
    "quest_22_deliver_bread_to_carmen": [
      "pan (bread)",
      "entregar (deliver)",
      "taberna (tavern)",
      "compra",
      "pan",
      "lleva"
    ],
    "quest_24_convince_pablo_to_join": [
      "festival (festival)",
      "equipo (team)",
      "unirse (join)",
      "pregúntale",
      "mateo",
      "habla",
      "pablo",
      "informa"
    ],
    "quest_31_fruit_for_the_feast": [
      "manzana (apple)",
      "fruta (fruit)",
      "sí (yes)",
      "encuentra",
      "manzana",
      "lleva"
    ],
    "quest_41_simple_gather_apple_for_lucas": [
      "manzana (apple)",
      "por favor (please)",
      "gracias (thank you)",
      "plaza",
      "del",
      "dale",
      "manzana"
    ]
  },
  "grammar_by_level": {
    "A0": [
      "Basic greetings and farewells (e.g., Hola, Adiós)",
      "Simple affirmations like 'Sí' and 'No'",
      "The alphabet and pronunciation basics",
      "Numbers 1-10 and basic colors",
      "Common polite expressions (e.g., Gracias, Por favor)"
    ],
    "A0+": [
      "Definite and indefinite articles (el, la, los, las, un, una)",
      "Basic present tense conjugation of regular verbs (-ar, -er, -ir)",
      "Simple questions with '¿Qué?', '¿Quién?', '¿Cómo?'",
      "Subject pronouns (yo, tú, él, ella, etc.)",
      "Basic adjective agreement and positioning"
    ],
    "A1": [
      "Present tense conjugation of common irregular verbs (ser, estar, ir, tener)",
      "Structure of simple sentences (subject-verb-object)",
      "Negation using 'no' before the verb",
      "Using question words in forming questions (e.g., ¿Dónde?, ¿Cuándo?)",
      "Introduction to gendered nouns and adjective-noun agreement"
    ],
    "A1+": [
      "Conjugation of stem-changing verbs in the present tense (e.g., poder, querer, jugar)",
      "Introduction to simple past tense (pretérito) for regular verbs",
      "Use of conjunctions (y, o, pero, porque) to form compound sentences",
      "Expressing likes/dislikes with 'gustar' and similar verbs",
      "Introduction to reflexive verbs (e.g., levantarse, bañarse)"
    ],
    "A2": [
      "Distinction between pretérito and imperfecto for past events",
      "Simple future tense using 'ir a + infinitive'",
      "Using 'ser' versus 'estar' for different types of 'to be'",
      "Introduction to conditionals with 'si' for simple conditions",
      "Direct and indirect object pronouns and their placement"
    ]
  },
  "_meta": {
    "target_language": "spanish",
    "native_language": "english",
    "total_quests_indexed": 9,
    "levels_covered": [
      "A0",
      "A0+",
      "A1",
      "A1+",
      "A2"
    ]
  }
}